{
  "Albums": "Álbumes",
  "AppDeviceValues": "Aplicación: {0}, Dispositivo: {1}",
  "Application": "Aplicación",
  "Artists": "Artistas",
  "AuthenticationSucceededWithUserName": "{0} autenticado correctamente",
  "Books": "Libros",
  "CameraImageUploadedFrom": "A new camera image has been uploaded from {0}",
  "Channels": "Canales",
  "ChapterNameValue": "Capítulo {0}",
  "Collections": "Colecciones",
  "DeviceOfflineWithName": "{0} se ha desconectado",
  "DeviceOnlineWithName": "{0} está conectado",
  "FailedLoginAttemptWithUserName": "Error al intentar iniciar sesión a partir de {0}",
  "Favorites": "Favoritos",
  "Folders": "Carpetas",
  "Games": "Juegos",
  "Genres": "Géneros",
  "HeaderAlbumArtists": "Artistas del Álbum",
  "HeaderCameraUploads": "Camera Uploads",
  "HeaderContinueWatching": "Continuar viendo",
  "HeaderFavoriteAlbums": "Álbumes favoritos",
  "HeaderFavoriteArtists": "Artistas favoritos",
  "HeaderFavoriteEpisodes": "Episodios favoritos",
  "HeaderFavoriteShows": "Programas favoritos",
  "HeaderFavoriteSongs": "Canciones favoritas",
  "HeaderLiveTV": "TV en vivo",
  "HeaderNextUp": "Siguiendo",
  "HeaderRecordingGroups": "Grupos de grabación",
  "HomeVideos": "Vídeos de inicio",
  "Inherit": "Heredar",
  "ItemAddedWithName": "{0} se ha añadido a la biblioteca",
  "ItemRemovedWithName": "{0} se elimina de la biblioteca",
  "LabelIpAddressValue": "Dirección IP: {0}",
  "LabelRunningTimeValue": "Tiempo de funcionamiento: {0}",
  "Latest": "Últimos",
  "MessageApplicationUpdated": "Se ha actualizado el servidor Jellyfin",
  "MessageApplicationUpdatedTo": "Jellyfin Server has been updated to {0}",
  "MessageNamedServerConfigurationUpdatedWithValue": "La sección de configuración del servidor {0} ha sido actualizado",
  "MessageServerConfigurationUpdated": "Se ha actualizado la configuración del servidor",
  "MixedContent": "Contenido mixto",
  "Movies": "Peliculas",
  "Music": "Música",
  "MusicVideos": "Videos musicales",
  "NameInstallFailed": "{0} installation failed",
  "NameSeasonNumber": "Temporada {0}",
  "NameSeasonUnknown": "Season Unknown",
  "NewVersionIsAvailable": "A new version of Jellyfin Server is available for download.",
  "NotificationOptionApplicationUpdateAvailable": "Actualización de la aplicación disponible",
  "NotificationOptionApplicationUpdateInstalled": "Actualización de la aplicación instalada",
  "NotificationOptionAudioPlayback": "Se inició la reproducción de audio",
  "NotificationOptionAudioPlaybackStopped": "Se detuvo la reproducción de audio",
  "NotificationOptionCameraImageUploaded": "Imagen de la cámara cargada",
  "NotificationOptionGamePlayback": "Se inició la reproducción del juego",
  "NotificationOptionGamePlaybackStopped": "Se detuvo la reproducción del juego",
  "NotificationOptionInstallationFailed": "Error de instalación",
  "NotificationOptionNewLibraryContent": "Nuevo contenido añadido",
  "NotificationOptionPluginError": "Error en plugin",
  "NotificationOptionPluginInstalled": "Plugin instalado",
  "NotificationOptionPluginUninstalled": "Plugin desinstalado",
  "NotificationOptionPluginUpdateInstalled": "Actualización del complemento instalada",
  "NotificationOptionServerRestartRequired": "Requiere reinicio del servidor",
  "NotificationOptionTaskFailed": "Error de tarea programada",
  "NotificationOptionUserLockedOut": "Usuario bloqueado",
  "NotificationOptionVideoPlayback": "Se inició la reproducción de vídeo",
  "NotificationOptionVideoPlaybackStopped": "Reproducción de vídeo detenida",
  "Photos": "Fotos",
  "Playlists": "Listas reproducción",
  "Plugin": "Plugin",
  "PluginInstalledWithName": "{0} se ha instalado",
  "PluginUninstalledWithName": "{0} se ha desinstalado",
  "PluginUpdatedWithName": "{0} se actualizó",
  "ProviderValue": "Proveedor: {0}",
  "ScheduledTaskFailedWithName": "{0} falló",
  "ScheduledTaskStartedWithName": "{0} iniciada",
  "ServerNameNeedsToBeRestarted": "{0} needs to be restarted",
  "Shows": "Series",
  "Songs": "Canciones",
  "StartupEmbyServerIsLoading": "Jellyfin Server se está cargando. Vuelve a intentarlo en breve.",
  "SubtitleDownloadFailureForItem": "Error al descargar subtítulos para {0}",
  "SubtitleDownloadFailureFromForItem": "Subtitles failed to download from {0} for {1}",
  "SubtitlesDownloadedForItem": "Descargar subtítulos para {0}",
  "Sync": "Sincronizar",
  "System": "Sistema",
  "TvShows": "Series TV",
  "User": "Usuario",
  "UserCreatedWithName": "El usuario {0} ha sido creado",
  "UserDeletedWithName": "El usuario {0} ha sido borrado",
  "UserDownloadingItemWithValues": "{0} está descargando {1}",
  "UserLockedOutWithName": "El usuario {0} ha sido bloqueado",
  "UserOfflineFromDevice": "{0} se ha desconectado de {1}",
  "UserOnlineFromDevice": "{0} está en línea desde {1}",
  "UserPasswordChangedWithName": "Se ha cambiado la contraseña para el usuario {0}",
  "UserPolicyUpdatedWithName": "User policy has been updated for {0}",
  "UserStartedPlayingItemWithValues": "{0} ha comenzado reproducir {1}",
  "UserStoppedPlayingItemWithValues": "{0} ha parado de reproducir {1}",
  "ValueHasBeenAddedToLibrary": "{0} has been added to your media library",
  "ValueSpecialEpisodeName": "Especial - {0}",
  "VersionNumber": "Versión {0}"
}
